odoo/addons/sale_stock_deposit/README.rst
odoo/addons/sale_stock_deposit/__init__.py
odoo/addons/sale_stock_deposit/__manifest__.py
odoo/addons/sale_stock_deposit/i18n/es.po
odoo/addons/sale_stock_deposit/models/__init__.py
odoo/addons/sale_stock_deposit/models/procurement_group.py
odoo/addons/sale_stock_deposit/models/product_product.py
odoo/addons/sale_stock_deposit/models/res_partner.py
odoo/addons/sale_stock_deposit/models/sale_order.py
odoo/addons/sale_stock_deposit/models/sale_order_line.py
odoo/addons/sale_stock_deposit/models/stock_location.py
odoo/addons/sale_stock_deposit/models/stock_picking.py
odoo/addons/sale_stock_deposit/models/stock_route.py
odoo/addons/sale_stock_deposit/models/stock_rule.py
odoo/addons/sale_stock_deposit/models/stock_warehouse.py
odoo/addons/sale_stock_deposit/security/ir.model.access.csv
odoo/addons/sale_stock_deposit/static/description/icon.png
odoo/addons/sale_stock_deposit/tests/__init__.py
odoo/addons/sale_stock_deposit/tests/test_sale_stock_deposit.py
odoo/addons/sale_stock_deposit/views/res_partner_views.xml
odoo/addons/sale_stock_deposit/views/stock_location.xml
odoo/addons/sale_stock_deposit/views/stock_quant_views.xml
odoo/addons/sale_stock_deposit/views/stock_route.xml
odoo/addons/sale_stock_deposit/wizards/__init__.py
odoo/addons/sale_stock_deposit/wizards/res_partner_stock_deposit_creation_wizard.py
odoo/addons/sale_stock_deposit/wizards/res_partner_stock_deposit_creation_wizard_views.xml
odoo_addon_sale_stock_deposit-16.0.1.3.0.dist-info/METADATA
odoo_addon_sale_stock_deposit-16.0.1.3.0.dist-info/WHEEL
odoo_addon_sale_stock_deposit-16.0.1.3.0.dist-info/top_level.txt
odoo_addon_sale_stock_deposit-16.0.1.3.0.dist-info/RECORD
